sqlalchemy_ocient/__init__.py
sqlalchemy_ocient/ocient.py
sqlalchemy_ocient/tests/__init__.py
sqlalchemy_ocient/tests/__main__.py
sqlalchemy_ocient/tests/conftest.py
sqlalchemy_ocient/tests/pytest.ini
sqlalchemy_ocient/tests/requirements.py
sqlalchemy_ocient/tests/test.cfg
sqlalchemy_ocient/tests/test_suite.py
sqlalchemy_ocient/version.py
sqlalchemy_ocient-2.0.0.dist-info/WHEEL
sqlalchemy_ocient-2.0.0.dist-info/METADATA
sqlalchemy_ocient-2.0.0.dist-info/entry_points.txt
sqlalchemy_ocient-2.0.0.dist-info/RECORD
