Metadata-Version: 2.1
Name: sqlalchemy_ocient
Author: Ocient Inc
Author-email: info@ocient.com
Home-page: https://www.ocient.com/
License: Apache License, Version 2.0
Summary: Ocient Hyperscale Data Warehouse SQLAlchemy Dialect
Classifier: Development Status :: 3 - Alpha
Classifier: Topic :: Database
Classifier: Topic :: Database :: Front-Ends
Classifier: Topic :: Software Development
Classifier: Topic :: Software Development :: Libraries :: Python Modules
Classifier: Intended Audience :: Developers
Classifier: License :: OSI Approved :: Apache Software License
Classifier: Typing :: Typed
Version: 2.0.0
